MANIFEST.in
README.rst
setup.cfg
setup.py
ctp_deps/__init__.py
ctp_deps/include/ThostFtdcMdApi.h
ctp_deps/include/ThostFtdcTraderApi.h
ctp_deps/include/ThostFtdcUserApiDataType.h
ctp_deps/include/ThostFtdcUserApiStruct.h
ctp_deps/lib/libthostmduserapi.so
ctp_deps/lib/libthostmduserapi.so.6.3.7
ctp_deps/lib/libthosttraderapi.so
ctp_deps/lib/libthosttraderapi.so.6.3.7
ctp_deps/misc/brokers.xml
ctp_deps/misc/error.dtd
ctp_deps/misc/error.xml
python_ctp_deps.egg-info/PKG-INFO
python_ctp_deps.egg-info/SOURCES.txt
python_ctp_deps.egg-info/dependency_links.txt
python_ctp_deps.egg-info/not-zip-safe
python_ctp_deps.egg-info/top_level.txt