Metadata-Version: 1.0
Name: python-ctp-deps
Version: 6.3.6.post20160606
Summary: Dynamic Shared Libraries (.so) for CTP
Home-page: https://github.com/mckelvin/python-ctp-deps
Author: PAN, Myautsai
Author-email: myautsai@gmail.com
License: BSD License
Keywords: ctp,sfit
Platform: UNKNOWN
